globaux/__init__.py
globaux/core.py
pixels/__init__.py
pixels/core.py
pixels/utils.py
codeboot-0.3.dist-info/METADATA
codeboot-0.3.dist-info/WHEEL
codeboot-0.3.dist-info/top_level.txt
codeboot-0.3.dist-info/RECORD
